CHANGELOG.md
README.md
monkeytoolbox/__init__.py
monkeytoolbox/code_utils.py
monkeytoolbox/decorators.py
monkeytoolbox/environment.py
monkeytoolbox/file_utils.py
monkeytoolbox/network_utils.py
monkeytoolbox/py.typed
monkeytoolbox/secure_directory.py
monkeytoolbox/secure_file.py
monkeytoolbox/threading.py
monkeytoolbox/windows_permissions.py
monkeytoolbox-1.0.0.dist-info/LICENSE
monkeytoolbox-1.0.0.dist-info/METADATA
monkeytoolbox-1.0.0.dist-info/WHEEL
monkeytoolbox-1.0.0.dist-info/RECORD
